{
    "shopName": "Sample Shop",
    "data": [{
        "name": "Mukiria Mururine AB Espresso Base",
        "country": "Kenya",
        "producer": "Mukiria Mururine",
        "availableAmount": "83 x 60kg bag",
        "price": "US$3.95 USD",
        "priceBaseUnit": "lbs",
        "varieties": ["SL-28", "SL-34"],
        "sensorialDescriptors": ["Honey", "Body/Fullness", "Fruity", "Black Currant", "Plum", "Sweet Aromatics", "Sweet", "Brown Sugar", "Overall Sweet", "Sweet & Sugary", "Black Cherry", "Red Grape"],
        "processingMethod": "Fully Washed",
        "cropYear": "2016",
        "packaging": "Grain Pro",
        "availability": "Spot",
        "warehouse": "Dupuy Houston - Houston, TX",
        "cuppingScore": 85.5,
        "screenSize": "15-17",
        "countryFlag": "#",
        "url": "#"
    }, {
        "name": "Marumi Society AA lot",
        "country": "Kenya",
        "producer": "Marumi Society",
        "availableAmount": "19 x 60kg bag",
        "price": "US$3.75 USD",
        "priceBaseUnit": "lbs",
        "varieties": ["SL-28", "SL-34"],
        "sensorialDescriptors": ["Honey", "Sweet", "Sweet & Sugary", "Black Currant", "Brown Sugar", "Overall Sweet", "Citrus Fruit", "Red Grape", "Black Tea", "Tropical Fruit", "Body/Fullness"],
        "processingMethod": "Fully Washed",
        "cropYear": "2016",
        "packaging": "Grain Pro",
        "availability": "Spot",
        "warehouse": "Dupuy Houston - Houston, TX",
        "cuppingScore": 86.75,
        "screenSize": "18-19",
        "countryFlag": "#",
        "url": "#"
    }, {
        "name": "Muthunzuuni Reserve AA",
        "country": "Kenya",
        "region": "Machakos",
        "producer": "Muthunzuuni Society",
        "availableAmount": "1 x 60kg bag",
        "price": "US$4.85 USD",
        "priceBaseUnit": "lbs",
        "varieties": ["SL-28"],
        "sensorialDescriptors": ["Green Grape", "Red Currant", "Black Cherry", "Sweet", "Savory", "Black Currant", "Sweet & Sugary", "Grapefruit", "Dark Chocolate", "Overall Sweet", "Sweet Pea", "Star Fruit", "Apricot", "Stone Fruit"],
        "processingMethod": "Fully Washed",
        "cropYear": "2016",
        "packaging": "Grain Pro",
        "availability": "Spot",
        "warehouse": "Dupuy Houston - Houston, TX",
        "cuppingScore": 87.5,
        "screenSize": "18-19",
        "countryFlag": "#",
        "url": "#"
    }, {
        "name": "Ndira Reserve AA",
        "country": "Kenya",
        "region": "Murang'a",
        "producer": "Ndira Cooperative Union",
        "availableAmount": "6 x 60kg bag",
        "price": "US$4.75 USD",
        "priceBaseUnit": "lbs",
        "varieties": ["SL-28"],
        "sensorialDescriptors": ["Lime", "Vanilla", "Green Grape", "Orange Blossom", "Lemon & Lime", "Floral", "Sweet", "Jasmine Honeysuckle", "Lemon", "Honey", "Sweet Aromatics", "Grapefruit", "Sweet & Sugary"],
        "processingMethod": "Fully Washed",
        "cropYear": "2016",
        "packaging": "Grain Pro",
        "availability": "Spot",
        "warehouse": "Dupuy Houston - Houston, TX",
        "cuppingScore": 87.0,
        "screenSize": "18-19",
        "countryFlag": "#",
        "url": "#"
    }],
    "fields": {
        "country": {
            "name": "Country",
            "type": "TEXT"
        },
        "sensorialDescriptors": {
            "name": "Descriptors",
            "type": "TEXT"
        },
        "packaging": {
            "name": "Packaging",
            "type": "TEXT"
        },
        "availability": {
            "name": "Availability",
            "type": "TEXT"
        },
        "warehouse": {
            "name": "Warehouse",
            "type": "TEXT"
        },
        "varieties": {
            "name": "Varieties",
            "type": "TEXT"
        },
        "screenSize": {
            "name": "Screen Size",
            "type": "TEXT"
        },
        "availableAmount": {
            "name": "Available Amount",
            "type": "NUMBER"
        },
        "countryFlag": {
            "name": "",
            "type": "IMAGE"
        },
        "cropYear": {
            "name": "Crop Year",
            "type": "TEXT"
        },
        "cuppingScore": {
            "name": "Score",
            "type": "NUMBER"
        },
        "price": {
            "name": "Price",
            "type": "NUMBER"
        },
        "name": {
            "name": "Name",
            "type": "TEXT"
        },
        "processingMethod": {
            "name": "Processing Method",
            "type": "TEXT"
        },
        "producer": {
            "name": "Producer",
            "type": "TEXT"
        },
        "region": {
            "name": "Region",
            "type": "TEXT"
        },
        "priceBaseUnit": {
            "name": "Price Unit",
            "type": "TEXT"
        }
    },
    "shopUrl": "#"
}